{
    "proc" : [
        {
              "name"  : "server"
            , "watch" : ["src/**/*.js", "!src/**/client/*", "!src/**/test/*"]
            , "exec"  : ["npm run buildserver"]
            , "cmd"   : {"proc": "node", "args": ["./bin/server/index.js"]}
            , "debug" : false 
            , "break" : false
         }
        ,
        {
             "name"    : "client"
           , "watch"   : ["src/**/*.js", "src/**/*.html", "!src/**/server/*", "!src/**/server.js", "!src/test/*"]
           , "exec"    : ["npm run build"]
           
        }
        ,
        {
             "name"    : "test"
           , "watch"   : ["src//**/test/*.js", "src/**/*.js", "!src/**/client/*"]
           , "exec"    : ["npm run buildserver"]
           , "cmd"     : {"proc": "node", "args": [
                                "./node_modules/mocha/bin/mocha"
                                , "-t"
                                , "200000"
                                , "--reporter" 
                                , "spec"
                                , "./bin/processor/test/procman.test.js"
                                ]
                         }
           , "dbg_idx" : 1
           
        }
    ]

    , "server" : { "url" : "http://localhost:3000", "timeout" : 8000 }
}
